scaleway_functions_python/__init__.py
scaleway_functions_python/framework/__init__.py
scaleway_functions_python/framework/v1/__init__.py
scaleway_functions_python/framework/v1/hints.py
scaleway_functions_python/local/__init__.py
scaleway_functions_python/local/context.py
scaleway_functions_python/local/event.py
scaleway_functions_python/local/infra.py
scaleway_functions_python/local/serving.py
scaleway_functions_python-0.2.3.dist-info/LICENSE
scaleway_functions_python-0.2.3.dist-info/METADATA
scaleway_functions_python-0.2.3.dist-info/WHEEL
scaleway_functions_python-0.2.3.dist-info/RECORD
