Metadata-Version: 2.3
Name: scaleway-functions-python
Version: 0.2.3
Summary: Utilities for testing your Python handlers for Scaleway Serverless Functions.
License: MIT
Keywords: serverless,scaleway,functions,cloud,faas
Author: Scaleway Serverless Team
Author-email: opensource@scaleway.com
Requires-Python: >=3.9,<3.14
Classifier: Development Status :: 4 - Beta
Classifier: Intended Audience :: Developers
Classifier: Intended Audience :: Information Technology
Classifier: License :: OSI Approved :: MIT License
Classifier: Programming Language :: Python
Classifier: Programming Language :: Python :: 3
Classifier: Programming Language :: Python :: 3.9
Classifier: Programming Language :: Python :: 3.10
Classifier: Programming Language :: Python :: 3.11
Classifier: Programming Language :: Python :: 3.12
Classifier: Programming Language :: Python :: 3.13
Classifier: Topic :: Internet
Classifier: Topic :: Software Development :: Libraries :: Application Frameworks
Requires-Dist: flask (>=2.2.2,<4.0.0)
Requires-Dist: typing-extensions (>=4.4.0,<5.0.0) ; python_version < "3.11"
Project-URL: Repository, https://github.com/scaleway/serverless-functions-python
